LICENSE
README.md
setup.py
whyclick/__init__.py
whyclick/chrome.py
whyclick/cli.py
whyclick/whyq.py
whyclick.egg-info/PKG-INFO
whyclick.egg-info/SOURCES.txt
whyclick.egg-info/dependency_links.txt
whyclick.egg-info/entry_points.txt
whyclick.egg-info/requires.txt
whyclick.egg-info/top_level.txt