Metadata-Version: 2.1
Name: whyclick
Version: 0.0.12
Summary: Cos I don't like to click
Home-page: https://github.com/alvations/whyclick
License: MIT
Platform: UNKNOWN
License-File: LICENSE
